odoo/addons/web_timeline/README.rst
odoo/addons/web_timeline/__init__.py
odoo/addons/web_timeline/__manifest__.py
odoo/addons/web_timeline/demo/ir_cron_view.xml
odoo/addons/web_timeline/i18n/de.po
odoo/addons/web_timeline/i18n/es.po
odoo/addons/web_timeline/i18n/fa.po
odoo/addons/web_timeline/i18n/fr.po
odoo/addons/web_timeline/i18n/he.po
odoo/addons/web_timeline/i18n/hr.po
odoo/addons/web_timeline/i18n/it.po
odoo/addons/web_timeline/i18n/nl_NL.po
odoo/addons/web_timeline/i18n/pt.po
odoo/addons/web_timeline/i18n/pt_BR.po
odoo/addons/web_timeline/i18n/tr.po
odoo/addons/web_timeline/i18n/web_timeline.pot
odoo/addons/web_timeline/i18n/zh_CN.po
odoo/addons/web_timeline/models/__init__.py
odoo/addons/web_timeline/models/ir_action.py
odoo/addons/web_timeline/models/ir_ui_view.py
odoo/addons/web_timeline/readme/CONFIGURE.md
odoo/addons/web_timeline/readme/CONTRIBUTORS.md
odoo/addons/web_timeline/readme/DESCRIPTION.md
odoo/addons/web_timeline/readme/ROADMAP.md
odoo/addons/web_timeline/readme/USAGE.md
odoo/addons/web_timeline/static/description/icon.png
odoo/addons/web_timeline/static/description/index.html
odoo/addons/web_timeline/static/lib/vis-timeline/vis-timeline-graph2d.css
odoo/addons/web_timeline/static/lib/vis-timeline/vis-timeline-graph2d.js
odoo/addons/web_timeline/static/src/views/timeline/timeline_arch_parser.esm.js
odoo/addons/web_timeline/static/src/views/timeline/timeline_canvas.esm.js
odoo/addons/web_timeline/static/src/views/timeline/timeline_canvas.scss
odoo/addons/web_timeline/static/src/views/timeline/timeline_controller.esm.js
odoo/addons/web_timeline/static/src/views/timeline/timeline_controller.xml
odoo/addons/web_timeline/static/src/views/timeline/timeline_model.esm.js
odoo/addons/web_timeline/static/src/views/timeline/timeline_renderer.esm.js
odoo/addons/web_timeline/static/src/views/timeline/timeline_renderer.xml
odoo/addons/web_timeline/static/src/views/timeline/timeline_view.esm.js
odoo_addon_web_timeline-18.0.1.0.2.dist-info/METADATA
odoo_addon_web_timeline-18.0.1.0.2.dist-info/WHEEL
odoo_addon_web_timeline-18.0.1.0.2.dist-info/top_level.txt
odoo_addon_web_timeline-18.0.1.0.2.dist-info/RECORD
